d3dshot/__init__.py
d3dshot/capture_output.py
d3dshot/d3dshot.py
d3dshot/display.py
d3dshot/capture_outputs/__init__.py
d3dshot/capture_outputs/numpy_capture_output.py
d3dshot/capture_outputs/numpy_float_capture_output.py
d3dshot/capture_outputs/pil_capture_output.py
d3dshot/capture_outputs/pytorch_capture_output.py
d3dshot/capture_outputs/pytorch_float_capture_output.py
d3dshot/capture_outputs/pytorch_float_gpu_capture_output.py
d3dshot/capture_outputs/pytorch_gpu_capture_output.py
d3dshot/dll/__init__.py
d3dshot/dll/d3d.py
d3dshot/dll/dxgi.py
d3dshot/dll/shcore.py
d3dshot/dll/user32.py
youdied/__init__.py
youdied/__main__.py
youdied/capture_and_detect.py
youdied/cli.py
youdied/exceptions.py
youdied/inspiration_message.py
youdied/storage.py
youdied-0.2.2.data/data/models/theModel/keras_metadata.pb
youdied-0.2.2.data/data/models/theModel/saved_model.pb
youdied-0.2.2.data/data/models/theModel/variables/variables.data-00000-of-00001
youdied-0.2.2.data/data/models/theModel/variables/variables.index
youdied-0.2.2.dist-info/LICENSE
youdied-0.2.2.dist-info/METADATA
youdied-0.2.2.dist-info/WHEEL
youdied-0.2.2.dist-info/entry_points.txt
youdied-0.2.2.dist-info/top_level.txt
youdied-0.2.2.dist-info/RECORD
