Metadata-Version: 2.1
Name: youdied
Version: 0.2.2
Summary: Captures screen and detect "you died"
Home-page: https://github.com/fauskanger/elden-ring-you-died/tree/main/youdied
Author: Thomas F
Author-email: 
License: MIT
Platform: UNKNOWN
Classifier: Development Status :: 4 - Beta
Classifier: Programming Language :: Python :: 3
Classifier: License :: OSI Approved :: MIT License
Classifier: Topic :: Games/Entertainment
Classifier: Topic :: Multimedia :: Graphics :: Capture :: Screen Capture
Classifier: Topic :: Scientific/Engineering :: Image Recognition
Requires-Python: >=3.7
License-File: LICENSE
Requires-Dist: numpy
Requires-Dist: pandas
Requires-Dist: tensorflow (>=2)
Requires-Dist: pillow (>=9)
Requires-Dist: comtypes (>=1.1.7)
